localization_checker/__init__.py
localization_checker/__main__.py
localization_checker/parser.py
localization_checker-0.0.8.dist-info/METADATA
localization_checker-0.0.8.dist-info/WHEEL
localization_checker-0.0.8.dist-info/top_level.txt
localization_checker-0.0.8.dist-info/RECORD
