Metadata-Version: 2.1
Name: localization-checker
Version: 0.0.8
Summary: Package to compare and complete all languages in your project with main language
Home-page: https://github.com/nachos-studio/localization_checker
Author: Armine Romanyuta
Author-email: romanyuta.armine@gmail.com
Classifier: Programming Language :: Python :: 3
Classifier: License :: OSI Approved :: MIT License
Classifier: Operating System :: OS Independent
Requires-Python: >=3.8
